aiotedee/__init__.py
aiotedee/bridge.py
aiotedee/const.py
aiotedee/exception.py
aiotedee/helpers.py
aiotedee/lock.py
aiotedee/py.typed
aiotedee/tedee_client.py
aiotedee-0.2.25.dist-info/licenses/LICENSE
aiotedee-0.2.25.dist-info/METADATA
aiotedee-0.2.25.dist-info/WHEEL
aiotedee-0.2.25.dist-info/top_level.txt
aiotedee-0.2.25.dist-info/RECORD
