Metadata-Version: 2.4
Name: aiotedee
Version: 0.2.25
Summary: A package to interact with Tedee locks using asyncio
Author-email: Josef Zweck <24647999+zweckj@users.noreply.github.com>
Maintainer-email: Josef Zweck <24647999+zweckj@users.noreply.github.com>
License: MIT License
Project-URL: Homepage, https://github.com/zweckj/aiotedee
Project-URL: Repository, https://github.com/zweckj/aiotedee
Project-URL: Documentation, https://github.com/zweckj/aiotedee
Keywords: Tedee,api,async,client
Classifier: Development Status :: 5 - Production/Stable
Classifier: Framework :: AsyncIO
Classifier: Intended Audience :: Developers
Classifier: Natural Language :: English
Classifier: License :: OSI Approved :: MIT License
Classifier: Programming Language :: Python
Classifier: Programming Language :: Python :: 3.12
Requires-Python: >=3.9
License-File: LICENSE
Requires-Dist: aiohttp>=3.8.1
Provides-Extra: dev
Requires-Dist: covdefaults==2.3.0; extra == "dev"
Requires-Dist: coverage==7.6.7; extra == "dev"
Requires-Dist: syrupy==4.7.2; extra == "dev"
Requires-Dist: pytest==8.3.3; extra == "dev"
Requires-Dist: pytest-asyncio==0.24.0; extra == "dev"
Requires-Dist: pytest-cov==6.0.0; extra == "dev"
Dynamic: license-file
